[{"tackle_total": 18.0, "apps": 34, "goals_scored": 19, "dispossessed_total": 83.0, "accurateCrosses_total": 2.0, "goals_conceded": 61, "key_passes": 52.0, "red_cards": 1, "name": "Christian Benteke", "age": 26, "end_cost": 74, "yellow_cards": 7, "next_year": 351.5, "ontarget_scoring_att": 43.0, "aerialWon_total": 269.0, "clean_sheets": 5, "clearance_total": 31.0, "interception_total": 9.0, "minutes": 2818, "own_goals": 0, "penalties_saved": 0, "togga_score": 502.0, "assists": 4, "saves": 0, "successful_dribbles": 23.0, "start_cost": 65}, {"tackle_total": 15.0, "apps": 38, "goals_scored": 15, "dispossessed_total": 51.0, "accurateCrosses_total": 23.0, "goals_conceded": 50, "key_passes": 81.0, "red_cards": 0, "name": "Rickie Lambert", "age": 35, "end_cost": 68, "yellow_cards": 2, "next_year": 410.5, "ontarget_scoring_att": 42.0, "aerialWon_total": 83.0, "clean_sheets": 8, "clearance_total": 35.0, "interception_total": 6.0, "minutes": 3126, "own_goals": 0, "penalties_saved": 0, "togga_score": 492.0, "assists": 8, "saves": 0, "successful_dribbles": 9.0, "start_cost": 60}, {"tackle_total": 7.0, "apps": 35, "goals_scored": 17, "dispossessed_total": 46.99999999999999, "accurateCrosses_total": 7.0, "goals_conceded": 40, "key_passes": 36.0, "red_cards": 0, "name": "Romelu Lukaku", "age": 24, "end_cost": 66, "yellow_cards": 3, "next_year": 413.0, "ontarget_scoring_att": 47.0, "aerialWon_total": 68.0, "clean_sheets": 3, "clearance_total": 9.0, "interception_total": 3.0, "minutes": 2005, "own_goals": 0, "penalties_saved": 0, "togga_score": 410.5, "assists": 7, "saves": 0, "successful_dribbles": 31.0, "start_cost": 65}, {"tackle_total": 20.0, "apps": 27, "goals_scored": 12, "dispossessed_total": 50.0, "accurateCrosses_total": 15.0, "goals_conceded": 25, "key_passes": 49.0, "red_cards": 0, "name": "Wayne Rooney", "age": 31, "end_cost": 116, "yellow_cards": 7, "next_year": 514.0, "ontarget_scoring_att": 35.0, "aerialWon_total": 15.0, "clean_sheets": 8, "clearance_total": 25.0, "interception_total": 13.0, "minutes": 2014, "own_goals": 1, "penalties_saved": 0, "togga_score": 348.5, "assists": 10, "saves": 0, "successful_dribbles": 12.0, "start_cost": 120}, {"tackle_total": 12.0, "apps": 34, "goals_scored": 7, "dispossessed_total": 45.0, "accurateCrosses_total": 1.0, "goals_conceded": 22, "key_passes": 33.0, "red_cards": 0, "name": "Peter Crouch", "age": 36, "end_cost": 60, "yellow_cards": 2, "next_year": 326.0, "ontarget_scoring_att": 21.0, "aerialWon_total": 281.0, "clean_sheets": 11, "clearance_total": 44.0, "interception_total": 9.0, "minutes": 2322, "own_goals": 0, "penalties_saved": 0, "togga_score": 346.0, "assists": 6, "saves": 0, "successful_dribbles": 5.0, "start_cost": 65}, {"tackle_total": 19.0, "apps": 34, "goals_scored": 11, "dispossessed_total": 48.0, "accurateCrosses_total": 1.0, "goals_conceded": 23, "key_passes": 34.0, "red_cards": 1, "name": "Olivier Giroud", "age": 30, "end_cost": 73, "yellow_cards": 3, "next_year": 445.5, "ontarget_scoring_att": 38.0, "aerialWon_total": 131.0, "clean_sheets": 10, "clearance_total": 44.0, "interception_total": 14.0, "minutes": 2331, "own_goals": 0, "penalties_saved": 0, "togga_score": 337.5, "assists": 4, "saves": 0, "successful_dribbles": 11.0, "start_cost": 90}, {"tackle_total": 23.0, "apps": 34, "goals_scored": 11, "dispossessed_total": 86.0, "accurateCrosses_total": 3.0, "goals_conceded": 61, "key_passes": 42.0, "red_cards": 0, "name": "Arouna Kon\u00e9", "age": 33, "end_cost": 69, "yellow_cards": 0, "next_year": 0, "ontarget_scoring_att": 36.0, "aerialWon_total": 19.0, "clean_sheets": 5, "clearance_total": 8.0, "interception_total": 13.0, "minutes": 2932, "own_goals": 0, "penalties_saved": 0, "togga_score": 335.5, "assists": 5, "saves": 0, "successful_dribbles": 45.0, "start_cost": 65}, {"tackle_total": 26.0, "apps": 30, "goals_scored": 12, "dispossessed_total": 83.0, "accurateCrosses_total": 3.0, "goals_conceded": 20, "key_passes": 39.0, "red_cards": 0, "name": "Sergio Ag\u00fcero", "age": 29, "end_cost": 111, "yellow_cards": 2, "next_year": 414.0, "ontarget_scoring_att": 36.0, "aerialWon_total": 5.0, "clean_sheets": 10, "clearance_total": 1.0, "interception_total": 10.0, "minutes": 1944, "own_goals": 0, "penalties_saved": 0, "togga_score": 326.0, "assists": 3, "saves": 0, "successful_dribbles": 56.0, "start_cost": 115}, {"tackle_total": 16.0, "apps": 24, "goals_scored": 7, "dispossessed_total": 50.0, "accurateCrosses_total": 1.0, "goals_conceded": 29, "key_passes": 34.0, "red_cards": 0, "name": "Andy Carroll", "age": 28, "end_cost": 83, "yellow_cards": 6, "next_year": 69.0, "ontarget_scoring_att": 23.0, "aerialWon_total": 224.0, "clean_sheets": 7, "clearance_total": 60.0, "interception_total": 12.0, "minutes": 1953, "own_goals": 0, "penalties_saved": 0, "togga_score": 311.0, "assists": 5, "saves": 0, "successful_dribbles": 6.0, "start_cost": 85}, {"tackle_total": 16.0, "apps": 34, "goals_scored": 11, "dispossessed_total": 42.0, "accurateCrosses_total": 1.0, "goals_conceded": 30, "key_passes": 31.0, "red_cards": 0, "name": "Jermain Defoe", "age": 34, "end_cost": 78, "yellow_cards": 4, "next_year": 22.0, "ontarget_scoring_att": 41.0, "aerialWon_total": 6.0, "clean_sheets": 10, "clearance_total": 3.0, "interception_total": 10.0, "minutes": 2411, "own_goals": 0, "penalties_saved": 0, "togga_score": 282.0, "assists": 5, "saves": 0, "successful_dribbles": 12.0, "start_cost": 75}, {"tackle_total": 39.0, "apps": 34, "goals_scored": 8, "dispossessed_total": 49.0, "accurateCrosses_total": 7.0, "goals_conceded": 30, "key_passes": 27.0, "red_cards": 0, "name": "Shane Long", "age": 30, "end_cost": 58, "yellow_cards": 3, "next_year": 115.0, "ontarget_scoring_att": 20.0, "aerialWon_total": 62.0, "clean_sheets": 10, "clearance_total": 18.0, "interception_total": 8.0, "minutes": 2151, "own_goals": 0, "penalties_saved": 0, "togga_score": 265.5, "assists": 6, "saves": 0, "successful_dribbles": 12.0, "start_cost": 60}, {"tackle_total": 18.0, "apps": 26, "goals_scored": 6, "dispossessed_total": 29.0, "accurateCrosses_total": 5.0, "goals_conceded": 18, "key_passes": 23.0, "red_cards": 0, "name": "Victor Anichebe", "age": 29, "end_cost": 43, "yellow_cards": 2, "next_year": 143.5, "ontarget_scoring_att": 21.0, "aerialWon_total": 73.0, "clean_sheets": 10, "clearance_total": 14.0, "interception_total": 5.0, "minutes": 1716, "own_goals": 0, "penalties_saved": 0, "togga_score": 229.0, "assists": 6, "saves": 0, "successful_dribbles": 7.0, "start_cost": 55}, {"goals_scored": 11, "goals_conceded": 15, "age": null, "red_cards": 0, "name": "Daniel Sturridge", "end_cost": 75, "yellow_cards": 2, "next_year": 414.0, "ontarget_scoring_att": 33.0, "clean_sheets": 7, "minutes": 1254, "penalties_saved": 0, "own_goals": 0, "togga_score": 189.0, "assists": 5, "saves": 0, "start_cost": 80}, {"tackle_total": 11.0, "apps": 25, "goals_scored": 7, "dispossessed_total": 45.0, "accurateCrosses_total": 17.0, "goals_conceded": 33, "key_passes": 14.000000000000002, "red_cards": 0, "name": "Hal Robson-Kanu", "age": 28, "end_cost": 42, "yellow_cards": 0, "next_year": 0, "ontarget_scoring_att": 14.0, "aerialWon_total": 25.0, "clean_sheets": 0, "clearance_total": 15.0, "interception_total": 20.0, "minutes": 1280, "own_goals": 0, "penalties_saved": 0, "togga_score": 176.0, "assists": 2, "saves": 0, "successful_dribbles": 7.000000000000001, "start_cost": 45}, {"tackle_total": 36.0, "apps": 27, "goals_scored": 1, "dispossessed_total": 38.0, "accurateCrosses_total": 3.0, "goals_conceded": 12, "key_passes": 22.0, "red_cards": 0, "name": "Danny Welbeck", "age": 26, "end_cost": 78, "yellow_cards": 1, "next_year": 210.5, "ontarget_scoring_att": 9.0, "aerialWon_total": 21.0, "clean_sheets": 4, "clearance_total": 12.0, "interception_total": 17.0, "minutes": 1301, "own_goals": 0, "penalties_saved": 0, "togga_score": 160.5, "assists": 4, "saves": 0, "successful_dribbles": 21.0, "start_cost": 85}, {"goals_scored": 6, "goals_conceded": 18, "age": null, "red_cards": 0, "name": "Lo\u00efc Remy", "end_cost": 54, "yellow_cards": 1, "next_year": 311.5, "ontarget_scoring_att": 17.0, "clean_sheets": 3, "minutes": 1141, "penalties_saved": 0, "own_goals": 0, "togga_score": 85.0, "assists": 0, "saves": 0, "start_cost": 60}, {"goals_scored": 1, "goals_conceded": 4, "age": null, "red_cards": 0, "name": "Mario Balotelli", "end_cost": 86, "yellow_cards": 2, "next_year": 0, "ontarget_scoring_att": 6.0, "clean_sheets": 3, "minutes": 591, "penalties_saved": 0, "own_goals": 0, "togga_score": 21.0, "assists": 1, "saves": 0, "start_cost": 90}, {"goals_scored": 1, "goals_conceded": 9, "age": null, "red_cards": 0, "name": "Fabio Borini", "end_cost": 72, "yellow_cards": 1, "next_year": 241.0, "ontarget_scoring_att": 5.0, "clean_sheets": 0, "minutes": 513, "penalties_saved": 0, "own_goals": 0, "togga_score": 16.0, "assists": 0, "saves": 0, "start_cost": 80}, {"goals_scored": 0, "goals_conceded": 7, "age": null, "red_cards": 0, "name": "Connor Wickham", "end_cost": 50, "yellow_cards": 0, "next_year": 72.0, "ontarget_scoring_att": 5.0, "clean_sheets": 1, "minutes": 443, "penalties_saved": 0, "own_goals": 0, "togga_score": 10.0, "assists": 0, "saves": 0, "start_cost": 55}, {"goals_scored": 1, "goals_conceded": 2, "age": null, "red_cards": 0, "name": "Fraizer Campbell", "end_cost": 49, "yellow_cards": 0, "next_year": 216.5, "clean_sheets": 1, "minutes": 264, "own_goals": 0, "penalties_saved": 0, "togga_score": 9, "assists": 0, "saves": 0, "start_cost": 55}]