{"element_type": 3, "squad_number": 10, "second_name": "Hazard", "transfers_in": 2580159, "special": false, "red_cards": 0, "status": "i", "first_name": "Eden", "transfers_out": 2197649, "minutes": 2985, "saves": 0, "code": 42786, "influence": "1044.6", "clean_sheets": 17, "ict_index": "351.6", "dreamteam_count": 5, "selected_by_percent": "30.6", "bonus": 33, "in_dreamteam": true, "cost_change_start": 5, "points_per_game": "6.2", "penalties_missed": 1, "total_points": 224, "own_goals": 0, "threat": "1162.0", "penalties_saved": 0, "yellow_cards": 3, "now_cost": 105, "goals_scored": 16, "assists": 9, "team": 4, "history": {"2014/15": {"dispossessed_score": -51.5, "aerialWonPerGame_total": 15.0, "ontarget_scoring_att_score": 66.0, "goals_conceded": 30, "total_through_ball_score": 22.0, "aerialWonPerGame": 0.39473684210526316, "corner_taken": 8.0, "togga_score": 663.0, "apps": 38, "ontarget_scoring_att": 33.0, "assists_score": 60, "dribbleWonPerGame": 4.7631578947368425, "ict_index": "0.0", "creativity": "0.0", "clean_sheets_score": 19, "successful_dribbles": 181.0, "start_cost": 100, "ea_index": 1002, "successful_dribbles_score": 181.0, "own_goals": 0, "yellow_cards": 2, "clean_sheets": 19, "penalties_missed": 1, "total_through_ball": 11.0, "assists": 10, "season_name": "2014/15", "key_passes_score": 200.0, "minsPlayed": 3379, "id": 5714, "season": 9, "end_cost": 108, "red_cards": 0, "threat": "0.0", "goals_conceded_score": 0, "goals_scored_score": 126, "bonus": 42, "minutes": 3373, "saves": 0, "influence": "0.0", "keyPassPerGame": 2.6315789473684212, "total_cross_score": 61.0, "penalties_saved": 0, "goals_scored": 14, "key_passes": 100.0, "yellow_cards_score": -6, "total_cross": 61.0, "element_code": 42786, "total_pass": 2217.0, "total_points": 233, "dispossessed": 103.0, "fouls": 12.0, "aerialWonPerGame_total_score": 7.5, "bps": 981}, "2013/14": {"dispossessed_score": -41.0, "aerialWonPerGame_total": 19.0, "ontarget_scoring_att_score": 64.0, "goals_conceded": 24, "total_through_ball_score": 24.0, "aerialWonPerGame": 0.5428571428571428, "corner_taken": 14.0, "togga_score": 618.5, "apps": 35, "ontarget_scoring_att": 32.0, "assists_score": 60, "dribbleWonPerGame": 3.7714285714285714, "ict_index": "0.0", "creativity": "0.0", "clean_sheets_score": 14, "successful_dribbles": 132.0, "start_cost": 95, "ea_index": 859, "successful_dribbles_score": 132.0, "own_goals": 0, "yellow_cards": 2, "clean_sheets": 14, "penalties_missed": 0, "total_through_ball": 12.0, "assists": 10, "season_name": "2013/14", "key_passes_score": 186.0, "minsPlayed": 2898, "id": 5013, "season": 8, "end_cost": 104, "red_cards": 0, "threat": "0.0", "goals_conceded_score": 0, "goals_scored_score": 126, "bonus": 23, "minutes": 2890, "saves": 0, "influence": "0.0", "keyPassPerGame": 2.657142857142857, "total_cross_score": 74.0, "penalties_saved": 0, "goals_scored": 14, "key_passes": 93.0, "yellow_cards_score": -6, "total_cross": 74.0, "element_code": 42786, "total_offside": 9.0, "total_pass": 1542.0, "total_points": 202, "dispossessed": 82.0, "aerialWonPerGame_total_score": 9.5, "bps": 218}, "2016/17": {"dispossessed_score": -30.5, "aerialWonPerGame_total": 20.0, "ontarget_scoring_att_score": 66.0, "goals_conceded": 29, "total_through_ball_score": 12.0, "aerialWonPerGame": 0.5555555555555556, "togga_score": 570.5, "apps": 36, "ontarget_scoring_att": 33.0, "dispossessed": 61.0, "dribbleWonPerGame": 3.9722222222222223, "ict_index": "351.6", "creativity": "1306.8", "clean_sheets_score": 17, "successful_dribbles": 143.0, "start_cost": 100, "ea_index": 0, "successful_dribbles_score": 143.0, "own_goals": 0, "yellow_cards": 3, "clean_sheets": 17, "penalties_missed": 1, "total_through_ball": 6.0, "assists": 9, "season_name": "2016/17", "key_passes_score": 176.0, "minsPlayed": 3007, "id": 7136, "season": 11, "end_cost": 105, "red_cards": 0, "threat": "1162.0", "goals_conceded_score": 0, "goals_scored_score": 144, "bonus": 33, "minutes": 2985, "saves": 0, "influence": "1044.6", "total_points": 224, "keyPassPerGame": 2.4444444444444446, "penalties_saved": 0, "goals_scored": 16, "key_passes": 88.0, "yellow_cards_score": -9, "element_code": 42786, "total_tackle": 18.0, "total_offside": 8.0, "total_pass": 1750.0, "assists_score": 54, "fouls": 19.0, "aerialWonPerGame_total_score": 10.0, "bps": 869}, "2015/16": {"dispossessed_score": -24.0, "aerialWonPerGame_total": 11.0, "ontarget_scoring_att_score": 28.0, "goals_conceded": 32, "total_through_ball_score": 14.0, "aerialWonPerGame": 0.3548387096774194, "corner_taken": 7.0, "togga_score": 342.5, "apps": 31, "ontarget_scoring_att": 14.0, "assists_score": 24, "dribbleWonPerGame": 2.870967741935484, "ict_index": "0.0", "creativity": "0.0", "clean_sheets_score": 5, "successful_dribbles": 89.0, "start_cost": 115, "ea_index": 476, "successful_dribbles_score": 89.0, "own_goals": 0, "yellow_cards": 2, "clean_sheets": 5, "penalties_missed": 0, "total_through_ball": 7.0, "assists": 4, "season_name": "2015/16", "key_passes_score": 132.0, "minsPlayed": 2192, "id": 6431, "season": 10, "end_cost": 109, "red_cards": 0, "threat": "0.0", "goals_conceded_score": 0, "goals_scored_score": 45, "bonus": 11, "minutes": 2193, "saves": 0, "influence": "0.0", "keyPassPerGame": 2.129032258064516, "total_cross_score": 44.0, "penalties_saved": 0, "goals_scored": 5, "key_passes": 66.0, "yellow_cards_score": -6, "total_cross": 44.0, "element_code": 42786, "total_offside": 10.0, "total_pass": 1415.0, "total_points": 104, "dispossessed": 48.0, "fouls": 15.0, "aerialWonPerGame_total_score": 5.5, "bps": 481}, "2012/13": {"dispossessed_score": -31.0, "aerialWonPerGame_total": 6.0, "ontarget_scoring_att_score": 52.0, "goals_conceded": 26, "total_through_ball_score": 18.0, "aerialWonPerGame": 0.17647058823529413, "corner_taken": 60.0, "togga_score": 511.0, "apps": 34, "ontarget_scoring_att": 26.0, "assists_score": 96, "dribbleWonPerGame": 1.8235294117647058, "ict_index": "0.0", "creativity": "0.0", "clean_sheets_score": 12, "successful_dribbles": 62.0, "start_cost": 95, "ea_index": 613, "successful_dribbles_score": 62.0, "own_goals": 0, "yellow_cards": 2, "clean_sheets": 12, "penalties_missed": 0, "total_through_ball": 9.0, "assists": 16, "season_name": "2012/13", "key_passes_score": 130.0, "minsPlayed": 2640, "id": 4316, "season": 7, "end_cost": 96, "red_cards": 0, "threat": "0.0", "goals_conceded_score": 0, "goals_scored_score": 81, "bonus": 22, "minutes": 2626, "saves": 0, "influence": "0.0", "keyPassPerGame": 1.911764705882353, "total_cross_score": 112.0, "penalties_saved": 0, "goals_scored": 9, "key_passes": 65.0, "yellow_cards_score": -6, "total_cross": 112.0, "element_code": 42786, "total_tackle": 28.0, "total_offside": 5.0, "total_pass": 1523.0, "total_points": 190, "dispossessed": 62.0, "fouls": 25.0, "aerialWonPerGame_total_score": 3.0, "bps": 0}}, "ep_next": "5.9", "value_season": "21.3", "ep_this": "1.5", "ea_index": 476, "id": 82, "name": "Eden Hazard", "goals_conceded": 29, "creativity": "1306.8", "bps": 869}